isozero/__init__.py
isozero/math_sim/__init__.py
isozero/math_sim/basewrapper.py
isozero/math_sim/claude.py
isozero/math_sim/main.py
isozero/math_sim/math_simulation.py
isozero/math_sim/math_wrapper.py
isozero/math_sim/openai_agent.py
isozero/math_sim/wrapper.py
isozero/reason_sim/__init__.py
isozero/reason_sim/__main__.py
isozero/reason_sim/base_wrapper.py
isozero/reason_sim/claude_agent.py
isozero/reason_sim/document_loader.py
isozero/reason_sim/document_search.py
isozero/reason_sim/huggingface_agent.py
isozero/reason_sim/openai_agent.py
isozero/reason_sim/question_answerer.py
isozero/reason_sim/reason_simulation.py
isozero/reason_sim/reason_wrapper.py
isozero/reason_sim/text_extractor.py
isozero-0.1.0.dist-info/LICENSE
isozero-0.1.0.dist-info/METADATA
isozero-0.1.0.dist-info/WHEEL
isozero-0.1.0.dist-info/entry_points.txt
isozero-0.1.0.dist-info/top_level.txt
isozero-0.1.0.dist-info/RECORD
