Metadata-Version: 2.1
Name: isozero
Version: 0.1.0
Summary: Enhance LLM Zero-Shot Responses through multi-step reasoning and document analysis
Home-page: https://github.com/iso-ai/isozero
Author: Jazmia Henry
Author-email: jazmiahenry@example.com
License: UNKNOWN
Platform: UNKNOWN
Classifier: Development Status :: 3 - Alpha
Classifier: Intended Audience :: Developers
Classifier: Intended Audience :: Science/Research
Classifier: License :: OSI Approved :: Apache Software License
Classifier: Operating System :: OS Independent
Classifier: Programming Language :: Python :: 3
Classifier: Programming Language :: Python :: 3.7
Classifier: Programming Language :: Python :: 3.8
Classifier: Programming Language :: Python :: 3.9
Classifier: Topic :: Scientific/Engineering :: Artificial Intelligence
Classifier: Topic :: Software Development :: Libraries :: Python Modules
Requires-Python: >=3.7
License-File: LICENSE
Requires-Dist: anthropic
Requires-Dist: openai
Requires-Dist: transformers
Requires-Dist: torch
Requires-Dist: numpy
Requires-Dist: pandas
Requires-Dist: tqdm
Requires-Dist: requests
Requires-Dist: beautifulsoup4
Requires-Dist: python-dotenv
Requires-Dist: scikit-learn
Requires-Dist: matplotlib
Requires-Dist: jsonschema
